{
  "uid": "P1DlVS",
  "name": "2:1",
  "description": "2 hard weeks followed by 1 rest week",
  "stepTitle": "MAP Block",
  "stepDescription": "Moderate Volume - 2:1",
  "icon": null,
  "plan": null,
  "hidden": null,
  "hideFitnessTestAlertMessage": null,
  "typename": null,
  "children": [
    {
      "uid": "qPYiw7",
      "name": "MAP Block - Medium Volume - 2:1",
      "description": null,
      "stepTitle": null,
      "stepDescription": null,
      "icon": null,
      "plan": {
        "id": "XmbShkfdJJ",
        "typename": null
      },
      "hidden": null,
      "hideFitnessTestAlertMessage": null,
      "typename": null,
      "children": null
    }
  ]
}