{
  "uid": "tCr0BD",
  "name": "No",
  "description": "Would you like to incorporate Strength Training into your plan? ",
  "stepTitle": "SBT GRVL Black Route",
  "stepDescription": null,
  "icon": null,
  "plan": null,
  "hidden": null,
  "hideFitnessTestAlertMessage": null,
  "typename": null,
  "children": [
    {
      "uid": "pojSBu55JM",
      "name": "2024 SBT GRVL - Black Course - High Volume - 2:1  (clone)",
      "description": null,
      "stepTitle": null,
      "stepDescription": null,
      "icon": null,
      "plan": {
        "id": "pojSBu55JM",
        "typename": null
      },
      "hidden": null,
      "hideFitnessTestAlertMessage": null,
      "typename": null,
      "children": null
    }
  ]
}