{
  "uid": "teWjXA",
  "name": "Pain Suckers Delight (\u0027hardest\u0027 route)",
  "description": "Knighthood Quest",
  "stepTitle": "Pain Suckers Delight (hardest route)",
  "stepDescription": null,
  "icon": null,
  "plan": null,
  "hidden": null,
  "hideFitnessTestAlertMessage": null,
  "typename": null,
  "children": [
    {
      "uid": "BaThjnAKAM",
      "name": "KoS Quest - Pain Suckers Delight (hardest)",
      "description": null,
      "stepTitle": null,
      "stepDescription": null,
      "icon": null,
      "plan": {
        "id": "BaThjnAKAM",
        "typename": null
      },
      "hidden": null,
      "hideFitnessTestAlertMessage": null,
      "typename": null,
      "children": null
    }
  ]
}