{
  "uid": "ytK4TR",
  "name": "65km",
  "description": "12 week training plan starting February 2",
  "stepTitle": "65km",
  "stepDescription": null,
  "icon": null,
  "plan": null,
  "hidden": null,
  "hideFitnessTestAlertMessage": null,
  "typename": null,
  "children": [
    {
      "uid": "tpcLR2fHCw",
      "name": "DR 60k 2024",
      "description": null,
      "stepTitle": null,
      "stepDescription": null,
      "icon": null,
      "plan": {
        "id": "tpcLR2fHCw",
        "typename": null
      },
      "hidden": null,
      "hideFitnessTestAlertMessage": null,
      "typename": null,
      "children": null
    },
    {
      "uid": "BJkYg8qpME",
      "name": "Dirty Reiver 65k 2026",
      "description": null,
      "stepTitle": null,
      "stepDescription": null,
      "icon": null,
      "plan": {
        "id": "BJkYg8qpME",
        "typename": null
      },
      "hidden": null,
      "hideFitnessTestAlertMessage": null,
      "typename": null,
      "children": null
    }
  ]
}